sec_package/__init__.py
sec_package/filetoimport.py
sec_package-0.1.76.dist-info/WHEEL
sec_package-0.1.76.dist-info/METADATA
sec_package-0.1.76.dist-info/RECORD
